tfw2v/__init__.py
tfw2v/similarity.py
tfw2v-0.3.dist-info/LICENSE.txt
tfw2v-0.3.dist-info/METADATA
tfw2v-0.3.dist-info/WHEEL
tfw2v-0.3.dist-info/top_level.txt
tfw2v-0.3.dist-info/RECORD
