Metadata-Version: 2.1
Name: tfw2v
Version: 0.3
Summary: A library for document similarity based on TF-IDF and Word2Vec.
Home-page: https://github.com/ruathudo/tfw2v
Author: Quan Duong
Author-email: quan.duong.vn@gmail.com
License: Attribution 4.0 International (CC BY 4.0)
Project-URL: Bug Reports, https://github.com/ruathudo/tfw2v/issues
Project-URL: Developer, https://ruathudo.github.io/
Keywords: document similarity,text similarity
Platform: UNKNOWN
Classifier: Development Status :: 5 - Production/Stable
Classifier: Intended Audience :: Developers
Classifier: Topic :: Text Processing :: Linguistic
Classifier: Programming Language :: Python :: 3
Requires-Python: >=3.6
License-File: LICENSE.txt
Requires-Dist: pandas
Requires-Dist: gensim (>=3.8)
Requires-Dist: parmap
